Workbook

Sheet YouTube Feature List
A1: MundiVeo — YouTube Feature Inventory & MVP Prioritization (MoSCoW)
A2: Every project member: fill in the 'MVP Priority' column per row. Compiled from current YouTube features plus notable historical/removed features (marked 'Legacy'). Not exhaustive of every minor UI tweak — focused on decision-worthy functionality.
A4: # | B4: Segment | C4: Feature / Function | D4: Description | E4: Status | F4: MVP Priority | G4: Notes / Rationale
A5: 1 | B5: 1. Account & Onboarding | C5: Single sign-on account | D5: One account (originally Google-linked) used to access the whole platform | E5: Current
A6: 2 | B6: 1. Account & Onboarding | C6: Custom @handle | D6: Unique, human-readable username separate from display name | E6: Current | G6: Introduced 2022
A7: 3 | B7: 1. Account & Onboarding | C7: Channel creation wizard | D7: Guided first-time setup flow for a new channel | E7: Current
A8: 4 | B8: 1. Account & Onboarding | C8: Profile picture & banner art | D8: Visual branding elements on the channel page | E8: Current
A9: 5 | B9: 1. Account & Onboarding | C9: Verification badge | D9: Checkmark shown once a channel passes a subscriber/identity threshold | E9: Current
A10: 6 | B10: 1. Account & Onboarding | C10: Multiple channels per account | D10: Manage several channels (e.g. brand accounts) under one login | E10: Current
A11: 7 | B11: 1. Account & Onboarding | C11: Two-factor authentication | D11: Extra login security step | E11: Current
A12: 8 | B12: 1. Account & Onboarding | C12: Account recovery flow | D12: Regain access via phone/email if locked out | E12: Current
A13: 9 | B13: 1. Account & Onboarding | C13: Channel trailer for non-subscribers | D13: Auto-played intro video shown only to people not yet subscribed | E13: Current
A14: 10 | B14: 1. Account & Onboarding | C14: Social links on channel | D14: Outbound links to other platforms shown on the About page | E14: Current
A15: 11 | B15: 2. Upload & Video Management | C15: Standard video upload | D15: Browser/app-based upload of a video file | E15: Current
A16: 12 | B16: 2. Upload & Video Management | C16: Bulk/batch upload | D16: Upload multiple videos in one session | E16: Current
A17: 13 | B17: 2. Upload & Video Management | C17: Privacy settings (Public/Unlisted/Private/Scheduled) | D17: Control who can find and view a video, or delay publishing | E17: Current
A18: 14 | B18: 2. Upload & Video Management | C18: Custom thumbnail upload | D18: Creator-chosen still image representing the video | E18: Current
... A22: 18 | B22: 2. Upload & Video Management | C22: Auto-detected chapters (AI) | D22: Platform automatically segments a video into chapters | E22: Current
A23: 19 | B23: 2. Upload & Video Management | C23: End screens | D23: Clickable subscribe/video/playlist links shown in the last ~20 seconds | E23: Current | G23: Replaced annotations, 2017+
A24: 20 | B24: 2. Upload & Video Management | C24: Cards | D24: Small clickable overlays (link, poll, merchandise) shown during playback | E24: Current | G24: Replaced annotations, 2017+
A25: 21 | B25: 2. Upload & Video Management | C25: Pop-up annotations | D25: Clickable text/image overlays drawn anywhere on the video frame | E25: Legacy - Removed | G25: Editor removed 2017-2018, all annotations deleted Jan 2019
A26: 22 | B26: 2. Upload & Video Management | C26: Caption/subtitle file upload | D26: Creator-supplied closed caption track | E26: Current
A27: 23 | B27: 2. Upload & Video Management | C27: Auto-dubbing into other languages (AI) | D27: Automatic AI-generated dubbed audio tracks, now free for all eligible creators | E27: Current | G27: Rolled out to all creators 2025-2026, 27 languages
A28: 24 | B28: 2. Upload & Video Management | C28: Creator-supplied dub audio tracks | D28: Manually uploaded alternate-language audio track | E28: Current
A29: 25 | B29: 2. Upload & Video Management | C29: Made-for-Kids toggle | D29: Legal/COPPA-style content classification at upload | E29: Current
A30: 26 | B30: 2. Upload & Video Management | C30: Built-in basic video editor | D30: In-browser trim, blur, audio swap, filters | E30: Current
A31: 27 | B31: 2. Upload & Video Management | C31: Automated copyright scan on upload | D31: Content ID check before/at publishing | E31: Current
A32: 28 | B32: 2. Upload & Video Management | C32: Scheduled premieres | D32: Video goes live at a set time with a countdown and live chat | E32: Current
A33: 29 | B33: 2. Upload & Video Management | C33: Replace uploaded video file | D33: Swap the underlying file while keeping URL/stats/comments | E33: Current
A34: 30 | B34: 2. Upload & Video Management | C34: Playlist creation & management | D34: Group videos into ordered or shuffled collections | E34: Current
A35: 31 | B35: 2. Upload & Video Management | C35: Series/season grouping | D35: Structure playlists as episodic seasons | E35: Current
A36: 32 | B36: 3. Video Player & Playback | C36: Adaptive-resolution streaming | D36: Automatic quality adjustment based on connection (144p-8K) | E36: Current
A37: 33 | B37: 3. Video Player & Playback | C37: Manual resolution selection | D37: Viewer overrides the automatic quality choice | E37: Current
A38: 34 | B38: 3. Video Player & Playback | C38: Playback speed control | D38: 0.25x-2x (or custom) speed adjustment | E38: Current
A39: 35 | B39: 3. Video Player & Playback | C39: Picture-in-picture / mini-player | D39: Keep watching in a small floating window while browsing | E39: Current
... A50: 46 | B50: 3. Video Player & Playback | C50: HDR playback | D50: High dynamic range video support | E50: Current
A51: 47 | B51: 3. Video Player & Playback | C51: Multi-camera / multiview live playback | D51: Watch multiple camera angles or streams at once (e.g. live sports) | E51: Current | G51: Expanding on YouTube TV, 2026
A52: 48 | B52: 3. Video Player & Playback | C52: Five-star rating system | D52: Rate a video 1-5 stars | E52: Legacy - Removed | G52: Replaced by like/dislike, 2009-2010
A53: 49 | B53: 3. Video Player & Playback | C53: Like / Dislike buttons | D53: Simple binary feedback on a video | E53: Current
A54: 50 | B54: 3. Video Player & Playback | C54: Public dislike counter | D54: Dislike count visible to all viewers, not just the creator | E54: Legacy - Removed | G54: Hidden from public view, Nov 2021
A55: 51 | B55: 3. Video Player & Playback | C55: Video Responses | D55: Reply to a video by publishing your own video response | E55: Legacy - Removed | G55: Removed ~2013
A56: 52 | B56: 4. Discovery, Search & Recommendations | C56: Personalized homepage feed | D56: Algorithmically ordered video grid on the homepage | E56: Current
A57: 53 | B57: 4. Discovery, Search & Recommendations | C57: Search with autocomplete | D57: Query suggestions while typing | E57: Current
A58: 54 | B58: 4. Discovery, Search & Recommendations | C58: Search filters | D58: Filter results by upload date, duration, type, features, etc. | E58: Current
A59: 55 | B59: 4. Discovery, Search & Recommendations | C59: Explore / Trending page | D59: Curated tabs for trending, music, gaming, news, etc. | E59: Current | G59: 'Trending' evolved into multi-tab 'Explore'
A60: 56 | B60: 4. Discovery, Search & Recommendations | C60: "Up next" suggested videos | D60: Recommended videos shown beside/after the current one | E60: Current
A61: 57 | B61: 4. Discovery, Search & Recommendations | C61: "Not interested" feedback | D61: Downvote a recommendation without leaving the video | E61: Current
A62: 58 | B62: 4. Discovery, Search & Recommendations | C62: "Don't recommend this channel" | D62: Suppress an entire channel from recommendations | E62: Current
A63: 59 | B63: 4. Discovery, Search & Recommendations | C63: Watch history | D63: Log of previously watched videos, used for personalization | E63: Current
A64: 60 | B64: 4. Discovery, Search & Recommendations | C64: Hashtag pages | D64: Aggregated feed of videos sharing a hashtag | E64: Current
A65: 61 | B65: 4. Discovery, Search & Recommendations | C65: Auto-generated topic/artist pages | D65: Platform-assembled channel-like pages for a subject or artist | E65: Current
A66: 62 | B66: 4. Discovery, Search & Recommendations | C66: Conversational AI search ("Ask") | D66: Chat-style search that understands follow-up questions | E66: Current | G66: Launched 2025-2026; ~20M monthly users by end of 2025
A67: 63 | B67: 4. Discovery, Search & Recommendations | C67: "More from this creator" / related channels | D67: Cross-promotion of similar or related channels | E67: Current
A68: 64 | B68: 4. Discovery, Search & Recommendations | C68: Auto-generated "Mix" playlists | D68: Platform-assembled endless playlists around a video/artist | E68: Current
A69: 65 | B69: 4. Discovery, Search & Recommendations | C69: Explainable recommendation reasons | D69: Plain-language reason shown for why a video was suggested | E69: Not present on YouTube | G69: Frequently requested transparency feature; N/A on YouTube today
A70: 66 | B70: 5. Channel Page & Branding | C70: Channel banner art | D70: Large header image on the channel page | E70: Current
A71: 67 | B71: 5. Channel Page & Branding | C71: Channel description / About page | D71: Free-text bio and channel details | E71: Current
A72: 68 | B72: 5. Channel Page & Branding | C72: Featured/pinned video or playlist | D72: Content pinned to the top of the channel homepage | E72: Current
A73: 69 | B73: 5. Channel Page & Branding | C73: Customizable channel sections | D73: Creator-arranged rows of playlists/content on the channel homepage | E73: Current
A74: 70 | B74: 5. Channel Page & Branding | C74: Channel tabs (Home/Videos/Shorts/Live/Playlists/Community/About) | D74: Standard navigation structure of a channel page | E74: Current
A75: 71 | B75: 5. Channel Page & Branding | C75: Channel keywords (SEO) | D75: Hidden metadata used for channel-level search relevance | E75: Current
A76: 72 | B76: 5. Channel Page & Branding | C76: Subscriber count visibility toggle | D76: Creator can hide their public subscriber count | E76: Current
A77: 73 | B77: 5. Channel Page & Branding | C77: Store / merchandise shelf | D77: Third-party merch integration shown under videos/channel | E77: Current
A78: 74 | B78: 5. Channel Page & Branding | C78: Ticketing / events shelf | D78: Promote live events/ticket sales under a video (regional availability) | E78: Current | G78: Availability varies by market
A79: 75 | B79: 6. Comments & Engagement | C79: Standard comment section | D79: Text comments under a video | E79: Current
A80: 76 | B80: 6. Comments & Engagement | C80: Threaded replies | D80: Nested replies to a comment | E80: Current
A81: 77 | B81: 6. Comments & Engagement | C81: Pinned comment | D81: Creator pins one comment to the top | E81: Current
A82: 78 | B82: 6. Comments & Engagement | C82: Creator heart on a comment | D82: Small heart icon shown when the creator likes a comment | E82: Current
A83: 79 | B83: 6. Comments & Engagement | C83: Comment sorting (Top/Newest) | D83: Viewer-selectable comment order | E83: Current
A84: 80 | B84: 6. Comments & Engagement | C84: Held-for-review comment queue | D84: Comments matching filters wait for creator approval | E84: Current
A85: 81 | B85: 6. Comments & Engagement | C85: Blocked words filter | D85: Auto-hide comments containing chosen words | E85: Current
A86: 82 | B86: 6. Comments & Engagement | C86: @mentions in comments | D86: Tag another channel/user in a comment | E86: Current
A87: 83 | B87: 6. Comments & Engagement | C87: AI comment summarization | D87: AI-generated summary of top themes in a comment section | E87: Current | G87: Rolled out 2024-2025
A88: 84 | B88: 6. Comments & Engagement | C88: In-app direct messaging | D88: Private messaging between users without leaving the app | E88: Current | G88: Wider rollout 2026
A89: 85 | B89: 6. Comments & Engagement | C89: Google+ integrated commenting | D89: Comments required a linked Google+ profile | E89: Legacy - Removed | G89: Introduced 2013, reverted 2015 after backlash
A90: 86 | B90: 7. Community Tab / Posts | C90: Text posts | D90: Short text-only update posted to subscribers | E90: Current
A91: 87 | B91: 7. Community Tab / Posts | C91: Image posts | D91: Photo update posted to subscribers | E91: Current
A92: 88 | B92: 7. Community Tab / Posts | C92: Poll posts | D92: Multiple-choice poll for subscribers to vote on | E92: Current
A93: 89 | B93: 7. Community Tab / Posts | C93: GIF posts | D93: Animated GIF update | E93: Current
A94: 90 | B94: 7. Community Tab / Posts | C94: Quiz posts | D94: Interactive quiz-style post | E94: Current
A95: 91 | B95: 7. Community Tab / Posts | C95: Subscriber-count gated eligibility | D95: Community tab only unlocked after reaching a subscriber threshold | E95: Current
A96: 92 | B96: 7. Community Tab / Posts | C96: YouTube Stories | D96: Short-lived vertical video updates visible only to subscribers, creator-only tool | E96: Legacy - Removed | G96: Discontinued June 2023
A97: 93 | B97: 8. Live Streaming | C97: Encoder-based live streaming | D97: Stream via OBS or similar broadcast software | E97: Current
A98: 94 | B98: 8. Live Streaming | C98: Mobile live streaming | D98: Go live directly from the mobile app | E98: Current
A99: 95 | B99: 8. Live Streaming | C99: Scheduled live streams / premieres | D99: Announce and countdown to a future live/scheduled watch event | E99: Current
A100: 96 | B100: 8. Live Streaming | C100: Live chat | D100: Real-time text chat alongside a live stream | E100: Current
A101: 97 | B101: 8. Live Streaming | C101: Live chat replay | D101: Chat messages replay in sync when watching the VOD afterward | E101: Current
A102: 98 | B102: 8. Live Streaming | C102: Super Chat | D102: Viewers pay to highlight/pin a chat message during a live stream | E102: Current
A103: 99 | B103: 8. Live Streaming | C103: Super Stickers | D103: Paid animated stickers shown in live chat | E103: Current
A104: 100 | B104: 8. Live Streaming | C104: Live polls | D104: Creator-run polls during a live stream | E104: Current
A105: 101 | B105: 8. Live Streaming | C105: Multi-camera / multiview live streams | D105: Multiple simultaneous camera angles or channels, viewer-selectable | E105: Current | G105: Expanding through 2026
A106: 102 | B106: 8. Live Streaming | C106: Clip creation from a live stream or VOD | D106: Viewers/creators cut a short shareable clip from a longer stream | E106: Current
A107: 103 | B107: 8. Live Streaming | C107: Co-streaming / guest features | D107: Bring another creator into your live stream as a guest | E107: Current
A108: 104 | B108: 9. Shorts (Short-form Video) | C108: Vertical short-form video upload | D108: Videos up to a few minutes, vertical/full-screen format | E108: Current | G108: Max length extended over time
A109: 105 | B109: 9. Shorts (Short-form Video) | C109: In-app Shorts camera | D109: Record directly within the app with built-in tools | E109: Current
A110: 106 | B110: 9. Shorts (Short-form Video) | C110: Remix (reuse audio/video from another Short) | D110: Build a new Short using another creator's audio or clip | E110: Current
A111: 107 | B111: 9. Shorts (Short-form Video) | C111: Green screen effect | D111: Replace background using another video/image as backdrop | E111: Current
A112: 108 | B112: 9. Shorts (Short-form Video) | C112: Music/sound library for Shorts | D112: Licensed audio tracks available to add to a Short | E112: Current
A113: 109 | B113: 9. Shorts (Short-form Video) | C113: Shorts shelf on homepage/channel | D113: Dedicated horizontal-scroll row for Shorts | E113: Current
A114: 110 | B114: 9. Shorts (Short-form Video) | C114: Shorts ad-revenue sharing | D114: Ad revenue pool distributed across Shorts views | E114: Current
...

Sheet Instructions
A1: MundiVeo — How to use this spreadsheet
A3: Goal: decide which YouTube-style features MundiVeo's MVP should launch with, before the platform is public and everyone starts requesting things.
A5: The MoSCoW method:
A6: MUST HAVE — the MVP is not viable without this. Launch blocker.
A7: SHOULD HAVE — important, but the MVP can technically launch without it for a short time.
A8: COULD HAVE — nice, adds polish, first to be cut if time/budget is tight.
A9: WON'T HAVE (this round) — deliberately excluded from this phase. Can be revisited later (including via community governance vote).
A10: NEEDS DISCUSSION — reasonable people disagree, or it needs more information (legal, cost, technical) before deciding.
A12: How to vote:
A13: 1. Go to the 'YouTube Feature List' tab.
A14: 2. For every row, use the dropdown in the 'MVP Priority' column to pick your preferred option.
A15: 3. Use the 'Notes / Rationale' column (or add your own name in brackets) to explain your reasoning, especially for anything you'd mark WON'T HAVE.
... A19: Note: this list focuses on decision-worthy functionality, not every minor UI tweak. If you spot something important missing, add a new row in the correct segment rather than starting a new list.

Sheet Summary Dashboard
A1: Summary Dashboard — auto-updates as the team fills in MVP Priority
A3: Segment | B3: MUST HAVE | C3: SHOULD HAVE | D3: COULD HAVE | E3: WON'T HAVE (this round) | F3: NEEDS DISCUSSION | G3: Total rows
A4: 1. Account & Onboarding | B4: =COUNTIFS('YouTube Feature List'!$B5:$B189,$A4,'YouTube Feature List'!$F5:$F189,B$3) -> 0 | C4: =COUNTIFS('YouTube Feature List'!$B5:$B189,$A4,'YouTube Feature List'!$F5:$F189,C$3) -> 0 | D4: =COUNTIFS('YouTube Feature List'!$B5:$B189,$A4,'YouTube Feature List'!$F5:$F189,D$3) -> 0 | E4: =COUNTIFS('YouTube Feature List'!$B5:$B189,$A4,'YouTube Feature List'!$F5:$F189,E$3) -> 0 | F4: =COUNTIFS('YouTube Feature List'!$B5:$B189,$A4,'YouTube Feature List'!$F5:$F189,F$3) -> 0 | G4: =COUNTIF('YouTube Feature List'!$B5:$B189,$A4) -> 10
A5: 2. Upload & Video Management | B5: =COUNTIFS('YouTube Feature List'!$B5:$B189,$A5,'YouTube Feature List'!$F5:$F189,B$3) -> 0 | C5: =COUNTIFS('YouTube Feature List'!$B5:$B189,$A5,'YouTube Feature List'!$F5:$F189,C$3) -> 0 | D5: =COUNTIFS('YouTube Feature List'!$B5:$B189,$A5,'YouTube Feature List'!$F5:$F189,D$3) -> 0 | E5: =COUNTIFS('YouTube Feature List'!$B5:$B189,$A5,'YouTube Feature List'!$F5:$F189,E$3) -> 0 | F5: =COUNTIFS('YouTube Feature List'!$B5:$B189,$A5,'YouTube Feature List'!$F5:$F189,F$3) -> 0 | G5: =COUNTIF('YouTube Feature List'!$B5:$B189,$A5) -> 21
A6: 3. Video Player & Playback | B6: =COUNTIFS('YouTube Feature List'!$B5:$B189,$A6,'YouTube Feature List'!$F5:$F189,B$3) -> 0 | C6: =COUNTIFS('YouTube Feature List'!$B5:$B189,$A6,'YouTube Feature List'!$F5:$F189,C$3) -> 0 | D6: =COUNTIFS('YouTube Feature List'!$B5:$B189,$A6,'YouTube Feature List'!$F5:$F189,D$3) -> 0 | E6: =COUNTIFS('YouTube Feature List'!$B5:$B189,$A6,'YouTube Feature List'!$F5:$F189,E$3) -> 0 | F6: =COUNTIFS('YouTube Feature List'!$B5:$B189,$A6,'YouTube Feature List'!$F5:$F189,F$3) -> 0 | G6: =COUNTIF('YouTube Feature List'!$B5:$B189,$A6) -> 20
A7: 4. Discovery, Search & Recommendations | B7: =COUNTIFS('YouTube Feature List'!$B5:$B189,$A7,'YouTube Feature List'!$F5:$F189,B$3) -> 0 | C7: =COUNTIFS('YouTube Feature List'!$B5:$B189,$A7,'YouTube Feature List'!$F5:$F189,C$3) -> 0 | D7: =COUNTIFS('YouTube Feature List'!$B5:$B189,$A7,'YouTube Feature List'!$F5:$F189,D$3) -> 0 | E7: =COUNTIFS('YouTube Feature List'!$B5:$B189,$A7,'YouTube Feature List'!$F5:$F189,E$3) -> 0 | F7: =COUNTIFS('YouTube Feature List'!$B5:$B189,$A7,'YouTube Feature List'!$F5:$F189,F$3) -> 0 | G7: =COUNTIF('YouTube Feature List'!$B5:$B189,$A7) -> 14
A8: 5. Channel Page & Branding | B8: =COUNTIFS('YouTube Feature List'!$B5:$B189,$A8,'YouTube Feature List'!$F5:$F189,B$3) -> 0 | C8: =COUNTIFS('YouTube Feature List'!$B5:$B189,$A8,'YouTube Feature List'!$F5:$F189,C$3) -> 0 | D8: =COUNTIFS('YouTube Feature List'!$B5:$B189,$A8,'YouTube Feature List'!$F5:$F189,D$3) -> 0 | E8: =COUNTIFS('YouTube Feature List'!$B5:$B189,$A8,'YouTube Feature List'!$F5:$F189,E$3) -> 0 | F8: =COUNTIFS('YouTube Feature List'!$B5:$B189,$A8,'YouTube Feature List'!$F5:$F189,F$3) -> 0 | G8: =COUNTIF('YouTube Feature List'!$B5:$B189,$A8) -> 9
A9: 6. Comments & Engagement | B9: =COUNTIFS('YouTube Feature List'!$B5:$B189,$A9,'YouTube Feature List'!$F5:$F189,B$3) -> 0 | C9: =COUNTIFS('YouTube Feature List'!$B5:$B189,$A9,'YouTube Feature List'!$F5:$F189,C$3) -> 0 | D9: =COUNTIFS('YouTube Feature List'!$B5:$B189,$A9,'YouTube Feature List'!$F5:$F189,D$3) -> 0 | E9: =COUNTIFS('YouTube Feature List'!$B5:$B189,$A9,'YouTube Feature List'!$F5:$F189,E$3) -> 0 | F9: =COUNTIFS('YouTube Feature List'!$B5:$B189,$A9,'YouTube Feature List'!$F5:$F189,F$3) -> 0 | G9: =COUNTIF('YouTube Feature List'!$B5:$B189,$A9) -> 11
A10: 7. Community Tab / Posts | B10: =COUNTIFS('YouTube Feature List'!$B5:$B189,$A10,'YouTube Feature List'!$F5:$F189,B$3) -> 0 | C10: =COUNTIFS('YouTube Feature List'!$B5:$B189,$A10,'YouTube Feature List'!$F5:$F189,C$3) -> 0 | D10: =COUNTIFS('YouTube Feature List'!$B5:$B189,$A10,'YouTube Feature List'!$F5:$F189,D$3) -> 0 | E10: =COUNTIFS('YouTube Feature List'!$B5:$B189,$A10,'YouTube Feature List'!$F5:$F189,E$3) -> 0 | F10: =COUNTIFS('YouTube Feature List'!$B5:$B189,$A10,'YouTube Feature List'!$F5:$F189,F$3) -> 0 | G10: =COUNTIF('YouTube Feature List'!$B5:$B189,$A10) -> 7
A11: 8. Live Streaming | B11: =COUNTIFS('YouTube Feature List'!$B5:$B189,$A11,'YouTube Feature List'!$F5:$F189,B$3) -> 0 | C11: =COUNTIFS('YouTube Feature List'!$B5:$B189,$A11,'YouTube Feature List'!$F5:$F189,C$3) -> 0 | D11: =COUNTIFS('YouTube Feature List'!$B5:$B189,$A11,'YouTube Feature List'!$F5:$F189,D$3) -> 0 | E11: =COUNTIFS('YouTube Feature List'!$B5:$B189,$A11,'YouTube Feature List'!$F5:$F189,E$3) -> 0 | F11: =COUNTIFS('YouTube Feature List'!$B5:$B189,$A11,'YouTube Feature List'!$F5:$F189,F$3) -> 0 | G11: =COUNTIF('YouTube Feature List'!$B5:$B189,$A11) -> 11
A12: 9. Shorts (Short-form Video) | B12: =COUNTIFS('YouTube Feature List'!$B5:$B189,$A12,'YouTube Feature List'!$F5:$F189,B$3) -> 0 | C12: =COUNTIFS('YouTube Feature List'!$B5:$B189,$A12,'YouTube Feature List'!$F5:$F189,C$3) -> 0 | D12: =COUNTIFS('YouTube Feature List'!$B5:$B189,$A12,'YouTube Feature List'!$F5:$F189,D$3) -> 0 | E12: =COUNTIFS('YouTube Feature List'!$B5:$B189,$A12,'YouTube Feature List'!$F5:$F189,E$3) -> 0 | F12: =COUNTIFS('YouTube Feature List'!$B5:$B189,$A12,'YouTube Feature List'!$F5:$F189,F$3) -> 0 | G12: =COUNTIF('YouTube Feature List'!$B5:$B189,$A12) -> 11
A13: 10. Notifications & Subscriptions | B13: =COUNTIFS('YouTube Feature List'!$B5:$B189,$A13,'YouTube Feature List'!$F5:$F189,B$3) -> 0 | C13: =COUNTIFS('YouTube Feature List'!$B5:$B189,$A13,'YouTube Feature List'!$F5:$F189,C$3) -> 0 | D13: =COUNTIFS('YouTube Feature List'!$B5:$B189,$A13,'YouTube Feature List'!$F5:$F189,D$3) -> 0 | E13: =COUNTIFS('YouTube Feature List'!$B5:$B189,$A13,'YouTube Feature List'!$F5:$F189,E$3) -> 0 | F13: =COUNTIFS('YouTube Feature List'!$B5:$B189,$A13,'YouTube Feature List'!$F5:$F189,F$3) -> 0 | G13: =COUNTIF('YouTube Feature List'!$B5:$B189,$A13) -> 6
A14: 11. Monetization & Creator Revenue | B14: =COUNTIFS('YouTube Feature List'!$B5:$B189,$A14,'YouTube Feature List'!$F5:$F189,B$3) -> 0 | C14: =COUNTIFS('YouTube Feature List'!$B5:$B189,$A14,'YouTube Feature List'!$F5:$F189,C$3) -> 0 | D14: =COUNTIFS('YouTube Feature List'!$B5:$B189,$A14,'YouTube Feature List'!$F5:$F189,D$3) -> 0 | E14: =COUNTIFS('YouTube Feature List'!$B5:$B189,$A14,'YouTube Feature List'!$F5:$F189,E$3) -> 0 | F14: =COUNTIFS('YouTube Feature List'!$B5:$B189,$A14,'YouTube Feature List'!$F5:$F189,F$3) -> 0 | G14: =COUNTIF('YouTube Feature List'!$B5:$B189,$A14) -> 14
A15: 12. Creator Studio & Analytics | B15: =COUNTIFS('YouTube Feature List'!$B5:$B189,$A15,'YouTube Feature List'!$F5:$F189,B$3) -> 0 | C15: =COUNTIFS('YouTube Feature List'!$B5:$B189,$A15,'YouTube Feature List'!$F5:$F189,C$3) -> 0 | D15: =COUNTIFS('YouTube Feature List'!$B5:$B189,$A15,'YouTube Feature List'!$F5:$F189,D$3) -> 0 | E15: =COUNTIFS('YouTube Feature List'!$B5:$B189,$A15,'YouTube Feature List'!$F5:$F189,E$3) -> 0 | F15: =COUNTIFS('YouTube Feature List'!$B5:$B189,$A15,'YouTube Feature List'!$F5:$F189,F$3) -> 0 | G15: =COUNTIF('YouTube Feature List'!$B5:$B189,$A15) -> 12
A16: 13. Moderation, Safety & Trust | B16: =COUNTIFS('YouTube Feature List'!$B5:$B189,$A16,'YouTube Feature List'!$F5:$F189,B$3) -> 0 | C16: =COUNTIFS('YouTube Feature List'!$B5:$B189,$A16,'YouTube Feature List'!$F5:$F189,C$3) -> 0 | D16: =COUNTIFS('YouTube Feature List'!$B5:$B189,$A16,'YouTube Feature List'!$F5:$F189,D$3) -> 0 | E16: =COUNTIFS('YouTube Feature List'!$B5:$B189,$A16,'YouTube Feature List'!$F5:$F189,E$3) -> 0 | F16: =COUNTIFS('YouTube Feature List'!$B5:$B189,$A16,'YouTube Feature List'!$F5:$F189,F$3) -> 0 | G16: =COUNTIF('YouTube Feature List'!$B5:$B189,$A16) -> 11
A17: 14. Accessibility & Localization | B17: =COUNTIFS('YouTube Feature List'!$B5:$B189,$A17,'YouTube Feature List'!$F5:$F189,B$3) -> 0 | C17: =COUNTIFS('YouTube Feature List'!$B5:$B189,$A17,'YouTube Feature List'!$F5:$F189,C$3) -> 0 | D17: =COUNTIFS('YouTube Feature List'!$B5:$B189,$A17,'YouTube Feature List'!$F5:$F189,D$3) -> 0 | E17: =COUNTIFS('YouTube Feature List'!$B5:$B189,$A17,'YouTube Feature List'!$F5:$F189,E$3) -> 0 | F17: =COUNTIFS('YouTube Feature List'!$B5:$B189,$A17,'YouTube Feature List'!$F5:$F189,F$3) -> 0 | G17: =COUNTIF('YouTube Feature List'!$B5:$B189,$A17) -> 6
A18: 15. Kids & Family Safety | B18: =COUNTIFS('YouTube Feature List'!$B5:$B189,$A18,'YouTube Feature List'!$F5:$F189,B$3) -> 0 | C18: =COUNTIFS('YouTube Feature List'!$B5:$B189,$A18,'YouTube Feature List'!$F5:$F189,C$3) -> 0 | D18: =COUNTIFS('YouTube Feature List'!$B5:$B189,$A18,'YouTube Feature List'!$F5:$F189,D$3) -> 0 | E18: =COUNTIFS('YouTube Feature List'!$B5:$B189,$A18,'YouTube Feature List'!$F5:$F189,E$3) -> 0 | F18: =COUNTIFS('YouTube Feature List'!$B5:$B189,$A18,'YouTube Feature List'!$F5:$F189,F$3) -> 0 | G18: =COUNTIF('YouTube Feature List'!$B5:$B189,$A18) -> 4
A19: 16. Premium / Paid Bundled Services | B19: =COUNTIFS('YouTube Feature List'!$B5:$B189,$A19,'YouTube Feature List'!$F5:$F189,B$3) -> 0 | C19: =COUNTIFS('YouTube Feature List'!$B5:$B189,$A19,'YouTube Feature List'!$F5:$F189,C$3) -> 0 | D19: =COUNTIFS('YouTube Feature List'!$B5:$B189,$A19,'YouTube Feature List'!$F5:$F189,D$3) -> 0 | E19: =COUNTIFS('YouTube Feature List'!$B5:$B189,$A19,'YouTube Feature List'!$F5:$F189,E$3) -> 0 | F19: =COUNTIFS('YouTube Feature List'!$B5:$B189,$A19,'YouTube Feature List'!$F5:$F189,F$3) -> 0 | G19: =COUNTIF('YouTube Feature List'!$B5:$B189,$A19) -> 8
A20: 17. AI & Emerging Creation Tools | B20: =COUNTIFS('YouTube Feature List'!$B5:$B189,$A20,'YouTube Feature List'!$F5:$F189,B$3) -> 0 | C20: =COUNTIFS('YouTube Feature List'!$B5:$B189,$A20,'YouTube Feature List'!$F5:$F189,C$3) -> 0 | D20: =COUNTIFS('YouTube Feature List'!$B5:$B189,$A20,'YouTube Feature List'!$F5:$F189,D$3) -> 0 | E20: =COUNTIFS('YouTube Feature List'!$B5:$B189,$A20,'YouTube Feature List'!$F5:$F189,E$3) -> 0 | F20: =COUNTIFS('YouTube Feature List'!$B5:$B189,$A20,'YouTube Feature List'!$F5:$F189,F$3) -> 0 | G20: =COUNTIF('YouTube Feature List'!$B5:$B189,$A20) -> 5
A21: 18. Discontinued / Historical (misc.) | B21: =COUNTIFS('YouTube Feature List'!$B5:$B189,$A21,'YouTube Feature List'!$F5:$F189,B$3) -> 0 | C21: =COUNTIFS('YouTube Feature List'!$B5:$B189,$A21,'YouTube Feature List'!$F5:$F189,C$3) -> 0 | D21: =COUNTIFS('YouTube Feature List'!$B5:$B189,$A21,'YouTube Feature List'!$F5:$F189,D$3) -> 0 | E21: =COUNTIFS('YouTube Feature List'!$B5:$B189,$A21,'YouTube Feature List'!$F5:$F189,E$3) -> 0 | F21: =COUNTIFS('YouTube Feature List'!$B5:$B189,$A21,'YouTube Feature List'!$F5:$F189,F$3) -> 0 | G21: =COUNTIF('YouTube Feature List'!$B5:$B189,$A21) -> 5
A22: TOTAL | B22: =SUM(B4:B21) -> 0 | C22: =SUM(C4:C21) -> 0 | D22: =SUM(D4:D21) -> 0 | E22: =SUM(E4:E21) -> 0 | F22: =SUM(F4:F21) -> 0 | G22: =SUM(G4:G21) -> 185
